sbp/__init__.py
sbp/_version.py
sbp/acquisition.py
sbp/bootload.py
sbp/constants.py
sbp/ext_events.py
sbp/file_io.py
sbp/flash.py
sbp/gnss.py
sbp/imu.py
sbp/integrity.py
sbp/linux.py
sbp/logging.py
sbp/mag.py
sbp/msg.py
sbp/navigation.py
sbp/ndb.py
sbp/observation.py
sbp/orientation.py
sbp/piksi.py
sbp/profiling.py
sbp/sbas.py
sbp/sbp2json.py
sbp/settings.py
sbp/signing.py
sbp/solution_meta.py
sbp/ssr.py
sbp/system.py
sbp/table.py
sbp/telemetry.py
sbp/tracking.py
sbp/user.py
sbp/utils.py
sbp/vehicle.py
sbp/version.py
sbp/client/__init__.py
sbp/client/forwarder.py
sbp/client/framer.py
sbp/client/handler.py
sbp/client/drivers/__init__.py
sbp/client/drivers/base_driver.py
sbp/client/drivers/cdc_driver.py
sbp/client/drivers/file_driver.py
sbp/client/drivers/network_drivers.py
sbp/client/drivers/pyftdi_driver.py
sbp/client/drivers/pyserial_driver.py
sbp/client/examples/__init__.py
sbp/client/examples/simple.py
sbp/client/examples/tcp.py
sbp/client/examples/udp.py
sbp/client/loggers/__init__.py
sbp/client/loggers/base_logger.py
sbp/client/loggers/json_logger.py
sbp/client/loggers/null_logger.py
sbp/client/loggers/rotating_logger.py
sbp/client/loggers/udp_logger.py
sbp/client/util/__init__.py
sbp/client/util/fftmonitor.py
sbp/client/util/settingmonitor.py
sbp-6.3.2.data/scripts/sbp2json
sbp2json/__init__.py
sbp2json/__main__.py
sbp-6.3.2.dist-info/METADATA
sbp-6.3.2.dist-info/WHEEL
sbp-6.3.2.dist-info/top_level.txt
sbp-6.3.2.dist-info/RECORD
