Metadata-Version: 2.4
Name: sbp
Version: 6.3.2
Summary: Python bindings for Swift Binary Protocol
Home-page: https://github.com/swift-nav/libsbp
Author: Swift Navigation
Author-email: dev@swift-nav.com
Platform: linux
Platform: osx
Platform: win32
Classifier: Intended Audience :: Developers
Classifier: Intended Audience :: Science/Research
Classifier: Operating System :: POSIX :: Linux
Classifier: Operating System :: MacOS :: MacOS X
Classifier: Operating System :: Microsoft :: Windows
Classifier: Programming Language :: Python
Classifier: Topic :: Scientific/Engineering :: Interface Engine/Protocol Translator
Classifier: Topic :: Software Development :: Libraries :: Python Modules
Classifier: Programming Language :: Python :: 3.7
Classifier: Programming Language :: Python :: 3.8
Classifier: Programming Language :: Python :: 3.9
Classifier: Programming Language :: Python :: 3.10
Requires-Dist: construct
Requires-Dist: pyftdi~=0.13.4
Requires-Dist: pylibftdi
Requires-Dist: pyserial
Provides-Extra: sbp2json
Requires-Dist: python-rapidjson~=1.0; extra == "sbp2json"
Requires-Dist: pybase64~=1.1; extra == "sbp2json"
Dynamic: author
Dynamic: author-email
Dynamic: classifier
Dynamic: description
Dynamic: home-page
Dynamic: platform
Dynamic: provides-extra
Dynamic: requires-dist
Dynamic: summary
